LICENSE
README.md
mcp_servers/__init__.py
mcp_servers/base.py
mcp_servers/brave.py
mcp_servers/cli_app.py
mcp_servers/exceptions.py
mcp_servers/filesystem.py
mcp_servers/logger.py
mcp_servers/searxng.py
mcp_servers/tavily.py
mcp_servers-0.1.10.dist-info/METADATA
mcp_servers-0.1.10.dist-info/WHEEL
mcp_servers-0.1.10.dist-info/entry_points.txt
mcp_servers-0.1.10.dist-info/licenses/LICENSE
mcp_servers-0.1.10.dist-info/RECORD
