Metadata-Version: 2.4
Name: mcp_servers
Version: 0.1.10
Summary: Simple MCP Server Collection, Packaged
Project-URL: Source, https://github.com/assagman/mcp-servers
Author-email: Sercan Sagman <sercan@sagmans.com>
License-File: LICENSE
Classifier: Development Status :: 1 - Planning
Classifier: Intended Audience :: Developers
Classifier: Intended Audience :: Information Technology
Classifier: License :: OSI Approved :: GNU General Public License v3 (GPLv3)
Classifier: Operating System :: OS Independent
Classifier: Programming Language :: Python :: 3.12
Classifier: Programming Language :: Python :: 3.13
Classifier: Topic :: Scientific/Engineering :: Artificial Intelligence
Classifier: Topic :: Software Development :: Libraries :: Python Modules
Requires-Python: <3.14,>=3.12
Requires-Dist: colorama
Requires-Dist: pydantic-ai==0.3.1
Requires-Dist: python-daemon
Provides-Extra: dev
Requires-Dist: black~=25.1.0; extra == 'dev'
Requires-Dist: build>=1.2.2; extra == 'dev'
Requires-Dist: pre-commit~=4.2.0; extra == 'dev'
Requires-Dist: psutil~=7.0.0; extra == 'dev'
Requires-Dist: ruff~=0.11.13; extra == 'dev'
Requires-Dist: twine>=5.1.1; extra == 'dev'
